setup.py
django_pagehelp.egg-info/PKG-INFO
django_pagehelp.egg-info/SOURCES.txt
django_pagehelp.egg-info/dependency_links.txt
django_pagehelp.egg-info/top_level.txt
pagehelp/__init__.py
pagehelp/admin.py
pagehelp/middleware.py
pagehelp/models.py
pagehelp/urls.py
pagehelp/utils.py
pagehelp/views.py