Metadata-Version: 1.0
Name: django-pagehelp
Version: 1.0
Summary: A Django application which provides contextual help for your site's pages.
Home-page: http://bitbucket.org/smileychris/django-pagehelp/
Author: Chris Beaven
Author-email: smileychris@gmail.com
License: UNKNOWN
Platform: UNKNOWN
Classifier: Development Status :: 4 - Beta
Classifier: Environment :: Web Environment
Classifier: Intended Audience :: Developers
Classifier: License :: OSI Approved :: MIT License
Classifier: Operating System :: OS Independent
Classifier: Programming Language :: Python
Classifier: Framework :: Django
